sssom_pydantic/__init__.py
sssom_pydantic/__main__.py
sssom_pydantic/api.py
sssom_pydantic/cli.py
sssom_pydantic/constants.py
sssom_pydantic/contrib/__init__.py
sssom_pydantic/contrib/ndex.py
sssom_pydantic/contrib/ontoportal.py
sssom_pydantic/contrib/sssompy.py
sssom_pydantic/contrib/wikidata.py
sssom_pydantic/database.py
sssom_pydantic/examples.py
sssom_pydantic/io.py
sssom_pydantic/models.py
sssom_pydantic/process.py
sssom_pydantic/py.typed
sssom_pydantic/query.py
sssom_pydantic/version.py
sssom_pydantic/web.py
sssom_pydantic-0.1.18.dist-info/licenses/LICENSE
sssom_pydantic-0.1.18.dist-info/WHEEL
sssom_pydantic-0.1.18.dist-info/entry_points.txt
sssom_pydantic-0.1.18.dist-info/METADATA
sssom_pydantic-0.1.18.dist-info/RECORD
