Metadata-Version: 2.4
Name: sssom_pydantic
Version: 0.1.18
Summary: Pydantic models for SSSOM
Keywords: snekpack,cookiecutter
Author: Charles Tapley Hoyt
Author-email: Charles Tapley Hoyt <cthoyt@gmail.com>
License-File: LICENSE
Classifier: Development Status :: 1 - Planning
Classifier: Environment :: Console
Classifier: Intended Audience :: Developers
Classifier: License :: OSI Approved :: MIT License
Classifier: Operating System :: OS Independent
Classifier: Framework :: Pytest
Classifier: Framework :: tox
Classifier: Framework :: Sphinx
Classifier: Natural Language :: English
Classifier: Programming Language :: Python
Classifier: Programming Language :: Python :: 3.10
Classifier: Programming Language :: Python :: 3.11
Classifier: Programming Language :: Python :: 3.12
Classifier: Programming Language :: Python :: 3.13
Classifier: Programming Language :: Python :: 3 :: Only
Classifier: Typing :: Typed
Requires-Dist: pydantic
Requires-Dist: curies>=0.12.5
Requires-Dist: pyyaml
Requires-Dist: pystow
Requires-Dist: sqlmodel ; extra == 'database'
Requires-Dist: fastapi ; extra == 'fastapi'
Requires-Dist: ndex2 ; extra == 'ndex'
Requires-Dist: ontoportal-client>0.0.6 ; extra == 'ontoportal'
Requires-Dist: sssom ; extra == 'sssompy'
Requires-Dist: pandas ; extra == 'sssompy'
Requires-Dist: wikidata-client ; extra == 'wikidata'
Requires-Dist: quickstatements-client ; extra == 'wikidata'
Requires-Dist: bioregistry ; extra == 'wikidata'
Maintainer: Charles Tapley Hoyt
Maintainer-email: Charles Tapley Hoyt <cthoyt@gmail.com>
Requires-Python: >=3.10
Project-URL: Bug Tracker, https://github.com/cthoyt/sssom-pydantic/issues
Project-URL: Documentation, https://sssom_pydantic.readthedocs.io
Project-URL: Funding, https://github.com/sponsors/cthoyt
Project-URL: Homepage, https://github.com/cthoyt/sssom-pydantic
Project-URL: Repository, https://github.com/cthoyt/sssom-pydantic.git
Provides-Extra: database
Provides-Extra: fastapi
Provides-Extra: ndex
Provides-Extra: ontoportal
Provides-Extra: sssompy
Provides-Extra: wikidata
